changesets_darwin_x64/__init__.py
changesets_darwin_x64/py.typed
changesets_darwin_x64/bin/changelog
changesets_darwin_x64-0.4.1.dist-info/METADATA
changesets_darwin_x64-0.4.1.dist-info/WHEEL
changesets_darwin_x64-0.4.1.dist-info/RECORD
