Metadata-Version: 2.4
Name: changesets-darwin-x64
Version: 0.4.1
Summary: Git-based changelog manager for JavaScript, Python, and Go projects.
Project-URL: Repository, https://github.com/dworthen/changelog
Author-email: Derek Worthen <worthend.derek@gmail.com>
License-Expression: MIT
Requires-Python: >=3.11
